ogd/core/__init__.py
ogd/core/exec/Commands.py
ogd/core/exec/Generators.py
ogd/core/exec/Parsers.py
ogd/core/exec/__init__.py
ogd/core/generators/Generator.py
ogd/core/generators/GeneratorLoader.py
ogd/core/generators/__init__.py
ogd/core/generators/detectors/Detector.py
ogd/core/generators/detectors/DetectorEvent.py
ogd/core/generators/detectors/__init__.py
ogd/core/generators/extractors/Extractor.py
ogd/core/generators/extractors/Feature.py
ogd/core/generators/extractors/PerCountFeature.py
ogd/core/generators/extractors/PerLevelFeature.py
ogd/core/generators/extractors/SessionFeature.py
ogd/core/generators/extractors/__init__.py
ogd/core/generators/extractors/builtin/BuiltinExtractor.py
ogd/core/generators/extractors/builtin/CountEvent.py
ogd/core/generators/extractors/builtin/Timespan.py
ogd/core/generators/extractors/builtin/__init__.py
ogd/core/generators/legacy/LegacyDetector.py
ogd/core/generators/legacy/LegacyFeature.py
ogd/core/generators/legacy/LegacyLoader.py
ogd/core/generators/legacy/__init__.py
ogd/core/interfaces/BQFirebaseInterface.py
ogd/core/interfaces/BigQueryCodingInterface.py
ogd/core/interfaces/BigQueryInterface.py
ogd/core/interfaces/CSVInterface.py
ogd/core/interfaces/CodingInterface.py
ogd/core/interfaces/EventInterface.py
ogd/core/interfaces/Interface.py
ogd/core/interfaces/MySQLInterface.py
ogd/core/interfaces/__init__.py
ogd/core/interfaces/outerfaces/DataOuterface.py
ogd/core/interfaces/outerfaces/DebugOuterface.py
ogd/core/interfaces/outerfaces/DictionaryOuterface.py
ogd/core/interfaces/outerfaces/TSVOuterface.py
ogd/core/interfaces/outerfaces/__init__.py
ogd/core/managers/EventManager.py
ogd/core/managers/ExportManager.py
ogd/core/managers/FeatureManager.py
ogd/core/managers/__init__.py
ogd/core/models/Event.py
ogd/core/models/FeatureData.py
ogd/core/models/__init__.py
ogd/core/models/enums/ExportMode.py
ogd/core/models/enums/ExtractionMode.py
ogd/core/models/enums/IDMode.py
ogd/core/models/enums/IterationMode.py
opengamedata_core-0.0.14.dist-info/LICENSE
opengamedata_core-0.0.14.dist-info/METADATA
opengamedata_core-0.0.14.dist-info/WHEEL
opengamedata_core-0.0.14.dist-info/top_level.txt
opengamedata_core-0.0.14.dist-info/RECORD
