Metadata-Version: 2.1
Name: opengamedata-core
Version: 0.0.14
Summary: A package for retrieving and processing event-based video game data. Additional authors: Nick Spevacek, Renee Li, John McCloskey, Zach Studdiford, Glenn Palmer, Haishuo Chen, Daus, Ameya Kshirsagar, Yunqing Xiao, Erik Harpstead, Manuel Jesus Gomez Moratilla
Author-email: Luke Swanson <superscription58@gmail.com>, David Gagnon <djgagnon@wisc.edu>
Project-URL: Homepage, https://github.com/opengamedata/opengamedata-core
Project-URL: Bug Tracker, https://github.com/opengamedata/opengamedata-core/issues
Project-URL: Documentation, https://opengamedata-doc.readthedocs.io/en/latest/index.html
Classifier: Programming Language :: Python :: 3
Classifier: License :: OSI Approved :: MIT License
Classifier: Operating System :: OS Independent
Requires-Python: >=3.10
License-File: LICENSE
